CHANGES.txt
LICENSE.txt
MANIFEST.in
README.md
README.rst
setup.cfg
setup.py
momentx/__init__.py
momentx/core.py
momentx/date.py
momentx/mystrptime.py
momentx.egg-info/PKG-INFO
momentx.egg-info/SOURCES.txt
momentx.egg-info/dependency_links.txt
momentx.egg-info/not-zip-safe
momentx.egg-info/requires.txt
momentx.egg-info/top_level.txt
momentx/contrib/__init__.py
momentx/contrib/momentx_wrapper.py