Metadata-Version: 1.1
Name: momentx
Version: 0.2.3
Summary: A lightweight wrapper around datetime with a focus on timezone handling and few dependencies (datetime, pytz and six).
Home-page: https://github.com/berlincode/momentx
Author: Ulf Bartel
Author-email: elastic.code@gmail.com
License: new-style BSD
Keywords: datetime,timezone,wrapper,pytz,simple,moment
Platform: UNKNOWN
Classifier: Intended Audience :: Developers
Classifier: License :: OSI Approved :: BSD License
Classifier: Natural Language :: English
Classifier: Programming Language :: Python :: 2.7
Classifier: Programming Language :: Python :: 3.5
Classifier: Programming Language :: Python :: 3.6
